azure/mgmt/search/__init__.py
azure/mgmt/search/_configuration.py
azure/mgmt/search/_patch.py
azure/mgmt/search/_search_management_client.py
azure/mgmt/search/_serialization.py
azure/mgmt/search/_vendor.py
azure/mgmt/search/_version.py
azure/mgmt/search/py.typed
azure/mgmt/search/aio/__init__.py
azure/mgmt/search/aio/_configuration.py
azure/mgmt/search/aio/_patch.py
azure/mgmt/search/aio/_search_management_client.py
azure/mgmt/search/aio/operations/__init__.py
azure/mgmt/search/aio/operations/_admin_keys_operations.py
azure/mgmt/search/aio/operations/_operations.py
azure/mgmt/search/aio/operations/_patch.py
azure/mgmt/search/aio/operations/_private_endpoint_connections_operations.py
azure/mgmt/search/aio/operations/_private_link_resources_operations.py
azure/mgmt/search/aio/operations/_query_keys_operations.py
azure/mgmt/search/aio/operations/_services_operations.py
azure/mgmt/search/aio/operations/_shared_private_link_resources_operations.py
azure/mgmt/search/models/__init__.py
azure/mgmt/search/models/_models_py3.py
azure/mgmt/search/models/_patch.py
azure/mgmt/search/models/_search_management_client_enums.py
azure/mgmt/search/operations/__init__.py
azure/mgmt/search/operations/_admin_keys_operations.py
azure/mgmt/search/operations/_operations.py
azure/mgmt/search/operations/_patch.py
azure/mgmt/search/operations/_private_endpoint_connections_operations.py
azure/mgmt/search/operations/_private_link_resources_operations.py
azure/mgmt/search/operations/_query_keys_operations.py
azure/mgmt/search/operations/_services_operations.py
azure/mgmt/search/operations/_shared_private_link_resources_operations.py
azure_mgmt_search-9.0.0.dist-info/LICENSE
azure_mgmt_search-9.0.0.dist-info/METADATA
azure_mgmt_search-9.0.0.dist-info/WHEEL
azure_mgmt_search-9.0.0.dist-info/top_level.txt
azure_mgmt_search-9.0.0.dist-info/RECORD
